d8s_html/__init__.py
d8s_html/html_data.py
d8s_html/html_data_temp_utils.py
tests/__init__.py
tests/test_html_data.py
d8s_html-0.6.1.dist-info/COPYING
d8s_html-0.6.1.dist-info/COPYING.LESSER
d8s_html-0.6.1.dist-info/METADATA
d8s_html-0.6.1.dist-info/WHEEL
d8s_html-0.6.1.dist-info/top_level.txt
d8s_html-0.6.1.dist-info/zip-safe
d8s_html-0.6.1.dist-info/RECORD
