Metadata-Version: 2.1
Name: d8s-html
Version: 0.6.1
Summary: Democritus functions for working with HTML.
Home-page: https://github.com/democritus-project/d8s-html
Author: Floyd Hightower
Author-email: floyd.hightower27@gmail.com
License: GNU Lesser General Public License v3
Keywords: democritus,utility,python,html,html-utility
Platform: UNKNOWN
Classifier: Development Status :: 2 - Pre-Alpha
Classifier: Intended Audience :: Developers
Classifier: License :: OSI Approved :: GNU Lesser General Public License v3 or later (LGPLv3+)
Classifier: Natural Language :: English
Classifier: Programming Language :: Python :: 3
Classifier: Programming Language :: Python :: 3.4
Classifier: Programming Language :: Python :: 3.5
Classifier: Programming Language :: Python :: 3.6
Classifier: Programming Language :: Python :: 3.7
Classifier: Programming Language :: Python :: 3.8
Classifier: Programming Language :: Python :: 3.9
License-File: COPYING
License-File: COPYING.LESSER
Requires-Dist: beautifulsoup4
Requires-Dist: d8s-networking (==0.*)
Requires-Dist: d8s-urls (==0.*)
Requires-Dist: html-to-json
Requires-Dist: html2text
Requires-Dist: importlib-metadata ; python_version < "3.8"
